{
  "run_id": 12,
  "task_class": "data",
  "task": "tell me about agentic AI in palantir foundry, and how a data engineer would use it",
  "assertions": [],
  "best_score": -Infinity,
  "best_recipe": null,
  "operator_stats": {
    "toggle_web": {
      "n": 13,
      "avg_reward": 0.37141397518528935
    },
    "change_nudge": {
      "n": 8,
      "avg_reward": 0.21234157995127945
    },
    "raise_top_k": {
      "n": 3,
      "avg_reward": 0.34072124923966207
    },
    "inject_memory": {
      "n": 3,
      "avg_reward": 0.34829364557468034
    },
    "inject_rag": {
      "n": 1,
      "avg_reward": 0.31299453942470684
    }
  },
  "baseline": 0.0,
  "improvement": 0,
  "timestamp": 1757118132
}